neojams/__init__.py
neojams/compatibility.py
neojams/core.py
neojams/display.py
neojams/eval.py
neojams/exceptions.py
neojams/models.py
neojams/nsconvert.py
neojams/schema.py
neojams/schemata/__init__.py
neojams/schemata/jams_schema.json
neojams/schemata/namespaces/beat/beat.json
neojams/schemata/namespaces/beat/position.json
neojams/schemata/namespaces/chord/chord.json
neojams/schemata/namespaces/chord/chord.re
neojams/schemata/namespaces/chord/harte.json
neojams/schemata/namespaces/chord/harte.re
neojams/schemata/namespaces/chord/roman.json
neojams/schemata/namespaces/chord/roman.re
neojams/schemata/namespaces/key/key_mode.json
neojams/schemata/namespaces/lyrics/bow.json
neojams/schemata/namespaces/lyrics/lyrics.json
neojams/schemata/namespaces/misc/blob.json
neojams/schemata/namespaces/misc/scaper.json
neojams/schemata/namespaces/misc/vector.json
neojams/schemata/namespaces/mood/thayer.json
neojams/schemata/namespaces/onset/onset.json
neojams/schemata/namespaces/pattern/jku.json
neojams/schemata/namespaces/pitch/class.json
neojams/schemata/namespaces/pitch/contour_hz.json
neojams/schemata/namespaces/pitch/hz.json
neojams/schemata/namespaces/pitch/midi.json
neojams/schemata/namespaces/pitch/note_hz.json
neojams/schemata/namespaces/pitch/note_midi.json
neojams/schemata/namespaces/segment/multi.json
neojams/schemata/namespaces/segment/open.json
neojams/schemata/namespaces/segment/salami_function.json
neojams/schemata/namespaces/segment/salami_lower.json
neojams/schemata/namespaces/segment/salami_upper.json
neojams/schemata/namespaces/segment/tut.json
neojams/schemata/namespaces/tag/cal10k.json
neojams/schemata/namespaces/tag/cal500.json
neojams/schemata/namespaces/tag/gtzan.json
neojams/schemata/namespaces/tag/medleydb_instruments.json
neojams/schemata/namespaces/tag/msd_tagtraum_cd1.json
neojams/schemata/namespaces/tag/msd_tagtraum_cd2.json
neojams/schemata/namespaces/tag/open.json
neojams/schemata/namespaces/tag/tag_audioset.json
neojams-0.1.2.dist-info/LICENSE
neojams-0.1.2.dist-info/METADATA
neojams-0.1.2.dist-info/WHEEL
neojams-0.1.2.dist-info/entry_points.txt
neojams-0.1.2.dist-info/RECORD
