Metadata-Version: 2.3
Name: neojams
Version: 0.1.2
Summary: A modernized Python package for working with the JAMS format, built on top of the original JAMS project
License: ISC
Keywords: audio,music,json,jams,mir
Author: Igor Bogicevic
Author-email: igor.bogicevic@gmail.com
Maintainer: Igor Bogicevic
Maintainer-email: igor.bogicevic@gmail.com
Requires-Python: >=3.12,<3.14
Classifier: Development Status :: 3 - Alpha
Classifier: License :: OSI Approved
Classifier: License :: OSI Approved :: ISC License (ISCL)
Classifier: Programming Language :: Python
Classifier: Programming Language :: Python :: 3
Classifier: Programming Language :: Python :: 3.12
Classifier: Programming Language :: Python :: 3.13
Requires-Dist: decorator (>=5.1.1,<6.0.0)
Requires-Dist: jsonschema (>=4.20.0,<5.0.0)
Requires-Dist: librosa (>=0.11.0,<0.12.0)
Requires-Dist: matplotlib (>=3.8.4,<4.0.0)
Requires-Dist: mir_eval (>=0.8.2,<0.9.0)
Requires-Dist: numpy (>=2.2.5,<3.0.0)
Requires-Dist: pandas (>=2.2.0,<3.0.0)
Requires-Dist: pydantic (>=2.5.3,<3.0.0)
Requires-Dist: sortedcontainers (>=2.4.0,<3.0.0)
Project-URL: Repository, https://github.com/probablyrobot/neojams
